operation_battleship_common_utilities/ApifyJobsCaller.py
operation_battleship_common_utilities/CandidateRequirementsDao.py
operation_battleship_common_utilities/CompanyDao.py
operation_battleship_common_utilities/CompanyDaoOld.py
operation_battleship_common_utilities/FailureLogger.py
operation_battleship_common_utilities/GenaricDatabaseDao.py
operation_battleship_common_utilities/GeographyHelper.py
operation_battleship_common_utilities/JobKeyWordsDao.py
operation_battleship_common_utilities/JobPostingDao.py
operation_battleship_common_utilities/JobResponsibilitiesDao.py
operation_battleship_common_utilities/JobSkillsDao.py
operation_battleship_common_utilities/JobTitleCategoryClassifier.py
operation_battleship_common_utilities/NomicAICaller.py
operation_battleship_common_utilities/NomicDao.py
operation_battleship_common_utilities/OpenAICaller.py
operation_battleship_common_utilities/PineConeDatabaseCaller.py
operation_battleship_common_utilities/__init__.py
OperationBattleshipCommonUtilities-0.4.17.dist-info/LICENSE
OperationBattleshipCommonUtilities-0.4.17.dist-info/METADATA
OperationBattleshipCommonUtilities-0.4.17.dist-info/WHEEL
OperationBattleshipCommonUtilities-0.4.17.dist-info/top_level.txt
OperationBattleshipCommonUtilities-0.4.17.dist-info/RECORD
