Metadata-Version: 2.1
Name: OperationBattleshipCommonUtilities
Version: 0.4.17
Summary: Classes and Utilities that are shared in the Operation Battleship Application
Home-page: https://github.com/CarawayLabs/OperationBattleshipCommonUtilities
Author: Matthew Caraway
Author-email: matthew@CarawayLabs.com
License: Apache-2.0 license
License-File: LICENSE
Requires-Dist: python-dotenv
Requires-Dist: apify-client
Requires-Dist: pandas
Requires-Dist: psycopg2
Requires-Dist: nomic
Requires-Dist: openai
Requires-Dist: pinecone-client
